[
  {
    "id": 1,
    "src": "/media-library/2013/03/a2.jpg",
    "size": 2158,
    "filename": "a2.jpg",
    "suggestedSlug": "a2",
    "title": "a2",
    "caption": "a2.jpg"
  },
  {
    "id": 2,
    "src": "/media-library/2013/03/bff.jpg",
    "size": 2161,
    "filename": "bff.jpg",
    "suggestedSlug": "bff",
    "title": "bff",
    "caption": "bff.jpg"
  },
  {
    "id": 3,
    "src": "/media-library/2013/03/broken.jpg",
    "size": 2170,
    "filename": "broken.jpg",
    "suggestedSlug": "broken",
    "title": "Broken",
    "caption": "broken.jpg"
  },
  {
    "id": 4,
    "src": "/media-library/2013/03/broken1.jpg",
    "size": 2173,
    "filename": "broken1.jpg",
    "suggestedSlug": "broken1",
    "title": "Broken 1",
    "caption": "broken1.jpg"
  },
  {
    "id": 5,
    "src": "/media-library/2013/03/post.jpg",
    "size": 2164,
    "filename": "post.jpg",
    "suggestedSlug": "post-2013-03",
    "title": "Post Image",
    "caption": "post.jpg"
  },
  {
    "id": 6,
    "src": "/media-library/2013/03/TSO.jpg",
    "size": 2161,
    "filename": "TSO.jpg",
    "suggestedSlug": "tso",
    "title": "TSO",
    "caption": "TSO.jpg"
  },
  {
    "id": 7,
    "src": "/media-library/2013/04/h1.jpg",
    "size": 2158,
    "filename": "h1.jpg",
    "suggestedSlug": "h1",
    "title": "h1",
    "caption": "h1.jpg"
  },
  {
    "id": 8,
    "src": "/media-library/2014/05/stolen-voices.jpg",
    "size": 2191,
    "filename": "stolen-voices.jpg",
    "suggestedSlug": "stolen-voices",
    "title": "Stolen Voices",
    "caption": "stolen-voices.jpg"
  },
  {
    "id": 9,
    "src": "/media-library/2014/09/b2.jpg",
    "size": 2158,
    "filename": "b2.jpg",
    "suggestedSlug": "b2",
    "title": "b2",
    "caption": "b2.jpg"
  },
  {
    "id": 10,
    "src": "/media-library/2014/09/huff2.png",
    "size": 2167,
    "filename": "huff2.png",
    "suggestedSlug": "huff2",
    "title": "huff2",
    "caption": "huff2.png"
  },
  {
    "id": 11,
    "src": "/media-library/2014/09/wttw.jpg",
    "size": 2164,
    "filename": "wttw.jpg",
    "suggestedSlug": "wttw",
    "title": "WTTW",
    "caption": "wttw.jpg"
  },
  {
    "id": 12,
    "src": "/media-library/2015/06/atso.jpg",
    "size": 2164,
    "filename": "atso.jpg",
    "suggestedSlug": "atso",
    "title": "atso",
    "caption": "atso.jpg"
  },
  {
    "id": 13,
    "src": "/media-library/2015/06/bb.jpg",
    "size": 2158,
    "filename": "bb.jpg",
    "suggestedSlug": "bb",
    "title": "bb",
    "caption": "bb.jpg"
  },
  {
    "id": 14,
    "src": "/media-library/2015/06/Broken1.jpg",
    "size": 2173,
    "filename": "Broken1.jpg",
    "suggestedSlug": "broken1-cap",
    "title": "Broken1",
    "caption": "Broken1.jpg"
  },
  {
    "id": 15,
    "src": "/media-library/2015/06/bwmelong.jpg",
    "size": 146152,
    "filename": "bwmelong.jpg",
    "suggestedSlug": "bwmelong",
    "title": "BW Me Long",
    "caption": "bwmelong.jpg"
  },
  {
    "id": 16,
    "src": "/media-library/2015/06/fb.jpg",
    "size": 146146,
    "filename": "fb.jpg",
    "suggestedSlug": "fb",
    "title": "fb",
    "caption": "fb.jpg"
  },
  {
    "id": 17,
    "src": "/media-library/2015/06/head.jpg",
    "size": 2164,
    "filename": "head.jpg",
    "suggestedSlug": "head",
    "title": "Head",
    "caption": "head.jpg"
  },
  {
    "id": 18,
    "src": "/media-library/2015/06/shy.jpg",
    "size": 507,
    "filename": "shy.jpg",
    "suggestedSlug": "shy-portrait",
    "title": "Shy Portrait",
    "caption": "shy.jpg"
  },
  {
    "id": 19,
    "src": "/media-library/2015/06/untitled.jpg",
    "size": 2176,
    "filename": "untitled.jpg",
    "suggestedSlug": "untitled",
    "title": "Untitled",
    "caption": "untitled.jpg"
  },
  {
    "id": 20,
    "src": "/media-library/2015/06/WTTW.jpg",
    "size": 2164,
    "filename": "WTTW.jpg",
    "suggestedSlug": "wttw-2015",
    "title": "WTTW 2015",
    "caption": "WTTW.jpg"
  },
  {
    "id": 21,
    "src": "/media-library/2016/05/3.jpg",
    "size": 2155,
    "filename": "3.jpg",
    "suggestedSlug": "photo-3",
    "title": "Photo 3",
    "caption": "3.jpg"
  },
  {
    "id": 22,
    "src": "/media-library/2016/07/3.jpg",
    "size": 503,
    "filename": "3.jpg",
    "suggestedSlug": "photo-3b",
    "title": "Photo 3B",
    "caption": "3.jpg"
  },
  {
    "id": 23,
    "src": "/media-library/2016/07/Sara-Payne-A-Mothers-Story.jpg",
    "size": 2230,
    "filename": "Sara-Payne-A-Mothers-Story.jpg",
    "suggestedSlug": "sara-payne",
    "title": "Sara Payne — A Mother's Story",
    "caption": "Sara-Payne-A-Mothers-Story.jpg"
  },
  {
    "id": 24,
    "src": "/media-library/2016/12/1-1.jpg",
    "size": 3351,
    "filename": "1-1.jpg",
    "suggestedSlug": "1-1",
    "title": "1-1",
    "caption": "1-1.jpg"
  },
  {
    "id": 25,
    "src": "/media-library/2016/12/123.jpg",
    "size": 507,
    "filename": "123.jpg",
    "suggestedSlug": "123",
    "title": "123",
    "caption": "123.jpg"
  },
  {
    "id": 26,
    "src": "/media-library/2016/12/2.jpg",
    "size": 2155,
    "filename": "2.jpg",
    "suggestedSlug": "2",
    "title": "2",
    "caption": "2.jpg"
  },
  {
    "id": 27,
    "src": "/media-library/2016/12/gameplan1.jpg",
    "size": 146153,
    "filename": "gameplan1.jpg",
    "suggestedSlug": "gameplan1",
    "title": "Gameplan",
    "caption": "gameplan1.jpg"
  },
  {
    "id": 28,
    "src": "/media-library/2017/06/51imuUWM3zL._SX325_BO1204203200_.jpg",
    "size": 2248,
    "filename": "51imuUWM3zL._SX325_BO1204203200_.jpg",
    "suggestedSlug": "51imu",
    "title": "51imuUWM3zL",
    "caption": "51imuUWM3zL._SX325_BO1204203200_.jpg"
  }
]
